ebookatty/__init__.py
ebookatty/__main__.py
ebookatty/cli.py
ebookatty/epub.py
ebookatty/metadata.py
ebookatty/mobi.py
ebookatty/standards.py
ebookatty-0.3.1.dist-info/LICENSE
ebookatty-0.3.1.dist-info/METADATA
ebookatty-0.3.1.dist-info/WHEEL
ebookatty-0.3.1.dist-info/entry_points.txt
ebookatty-0.3.1.dist-info/top_level.txt
ebookatty-0.3.1.dist-info/RECORD
