Metadata-Version: 2.1
Name: ebookatty
Version: 0.3.1
Summary: Tools for extracting Metadata from EPUB MOBI and other kindle formats
Home-page: https://github.com/alexpdev/ebookatty
Author: alexpdev
Author-email: alexpdev@protonmail.com
License: GNU LGPL v3
Project-URL: Source Code, https://github.com/alexpdev/ebookatty
Keywords: ebook,metadata,mobi,epub
Classifier: Programming Language :: Python :: 3
Classifier: License :: OSI Approved :: GNU Lesser General Public License v3 (LGPLv3)
Classifier: Operating System :: OS Independent
Classifier: Development Status :: 3 - Alpha
Classifier: Programming Language :: Python :: 3.3
Classifier: Programming Language :: Python :: 3.4
Classifier: Programming Language :: Python :: 3.5
Classifier: Programming Language :: Python :: 3.6
Classifier: Programming Language :: Python :: 3.7
Classifier: Programming Language :: Python :: 3.8
Classifier: Programming Language :: Python :: 3.9
Requires-Python: >=3.6
License-File: LICENSE
